Workbook

Sheet Inputs
A1: Mutual Fund vs ETF Fee Impact Calculator
A3: Input | B3: Value | C3: Format | D3: Notes
A4: Initial investment | B4: 10000 | C4: $ | D4: Starting amount invested today
A5: Annual contribution | B5: 5000 | C5: $ | D5: Amount invested every year
A6: Investment period | B6: 30 | C6: Years | D6: How long money stays invested
A7: Expected gross return | B7: 0.08 | C7: % | D7: Annual return before fund fees
A8: Mutual fund MER | B8: 0.02 | C8: % | D8: Annual management expense ratio
A9: ETF MER | B9: 0.002 | C9: % | D9: Annual management expense ratio
A11: Calculated Input | B11: Value | C11: Formula | D11: Meaning
A12: Mutual fund net return | B12: =B7-B8 -> 0.06 | C12: =Gross return - Mutual fund MER | D12: Return after annual fee
A13: ETF net return | B13: =B7-B9 -> 0.078 | C13: =Gross return - ETF MER | D13: Return after annual fee
B14: =B13-B12 -> 0.018

Sheet Yearly Calculation
A1: Year-by-Year Growth Comparison
A3: Year | B3: Mutual Fund Start Value | C3: MF Contribution | D3: MF Net Return | E3: Mutual Fund End Value | F3: ETF Start Value | G3: ETF Contribution | H3: ETF End Value
A4: 0 | B4: =Inputs!$B$4 -> 10000 | C4: 0 | D4: =Inputs!$B$12 -> 0.06 | E4: =B4 -> 10000 | F4: =Inputs!$B$4 -> 10000 | G4: 0 | H4: =F4 -> 10000
A5: 1 | B5: =E4 -> 10000 | C5: =Inputs!$B$5 -> 5000 | D5: =Inputs!$B$12 -> 0.06 | E5: =(B5+C5)*(1+D5) -> 15900 | F5: =H4 -> 10000 | G5: =Inputs!$B$5 -> 5000 | H5: =(F5+G5)*(1+Inputs!$B$13) -> 16170
A6: 2 | B6: =E5 -> 15900 | C6: =Inputs!$B$5 -> 5000 | D6: =Inputs!$B$12 -> 0.06 | E6: =(B6+C6)*(1+D6) -> 22154 | F6: =H5 -> 16170 | G6: =Inputs!$B$5 -> 5000 | H6: =(F6+G6)*(1+Inputs!$B$13) -> 22821.26
A7: 3 | B7: =E6 -> 22154 | C7: =Inputs!$B$5 -> 5000 | D7: =Inputs!$B$12 -> 0.06 | E7: =(B7+C7)*(1+D7) -> 28783.24 | F7: =H6 -> 22821.26 | G7: =Inputs!$B$5 -> 5000 | H7: =(F7+G7)*(1+Inputs!$B$13) -> 29991.318
A8: 4 | B8: =E7 -> 28783.24 | C8: =Inputs!$B$5 -> 5000 | D8: =Inputs!$B$12 -> 0.06 | E8: =(B8+C8)*(1+D8) -> 35810.234 | F8: =H7 -> 29991.318 | G8: =Inputs!$B$5 -> 5000 | H8: =(F8+G8)*(1+Inputs!$B$13) -> 37720.641
A9: 5 | B9: =E8 -> 35810.234 | C9: =Inputs!$B$5 -> 5000 | D9: =Inputs!$B$12 -> 0.06 | E9: =(B9+C9)*(1+D9) -> 43258.848 | F9: =H8 -> 37720.641 | G9: =Inputs!$B$5 -> 5000 | H9: =(F9+G9)*(1+Inputs!$B$13) -> 46052.851
A10: 6 | B10: =E9 -> 43258.848 | C10: =Inputs!$B$5 -> 5000 | D10: =Inputs!$B$12 -> 0.06 | E10: =(B10+C10)*(1+D10) -> 51154.379 | F10: =H9 -> 46052.851 | G10: =Inputs!$B$5 -> 5000 | H10: =(F10+G10)*(1+Inputs!$B$13) -> 55034.973
A11: 7 | B11: =E10 -> 51154.379 | C11: =Inputs!$B$5 -> 5000 | D11: =Inputs!$B$12 -> 0.06 | E11: =(B11+C11)*(1+D11) -> 59523.642 | F11: =H10 -> 55034.973 | G11: =Inputs!$B$5 -> 5000 | H11: =(F11+G11)*(1+Inputs!$B$13) -> 64717.701
A12: 8 | B12: =E11 -> 59523.642 | C12: =Inputs!$B$5 -> 5000 | D12: =Inputs!$B$12 -> 0.06 | E12: =(B12+C12)*(1+D12) -> 68395.061 | F12: =H11 -> 64717.701 | G12: =Inputs!$B$5 -> 5000 | H12: =(F12+G12)*(1+Inputs!$B$13) -> 75155.682
A13: 9 | B13: =E12 -> 68395.061 | C13: =Inputs!$B$5 -> 5000 | D13: =Inputs!$B$12 -> 0.06 | E13: =(B13+C13)*(1+D13) -> 77798.764 | F13: =H12 -> 75155.682 | G13: =Inputs!$B$5 -> 5000 | H13: =(F13+G13)*(1+Inputs!$B$13) -> 86407.825
A14: 10 | B14: =E13 -> 77798.764 | C14: =Inputs!$B$5 -> 5000 | D14: =Inputs!$B$12 -> 0.06 | E14: =(B14+C14)*(1+D14) -> 87766.69 | F14: =H13 -> 86407.825 | G14: =Inputs!$B$5 -> 5000 | H14: =(F14+G14)*(1+Inputs!$B$13) -> 98537.636
A15: 11 | B15: =E14 -> 87766.69 | C15: =Inputs!$B$5 -> 5000 | D15: =Inputs!$B$12 -> 0.06 | E15: =(B15+C15)*(1+D15) -> 98332.692 | F15: =H14 -> 98537.636 | G15: =Inputs!$B$5 -> 5000 | H15: =(F15+G15)*(1+Inputs!$B$13) -> 111613.57
A16: 12 | B16: =E15 -> 98332.692 | C16: =Inputs!$B$5 -> 5000 | D16: =Inputs!$B$12 -> 0.06 | E16: =(B16+C16)*(1+D16) -> 109532.65 | F16: =H15 -> 111613.57 | G16: =Inputs!$B$5 -> 5000 | H16: =(F16+G16)*(1+Inputs!$B$13) -> 125709.43
... A34: 30 | B34: =E33 -> 444474.81 | C34: =Inputs!$B$5 -> 5000 | D34: =Inputs!$B$12 -> 0.06 | E34: =(B34+C34)*(1+D34) -> 476443.3 | F34: =H33 -> 629346.32 | G34: =Inputs!$B$5 -> 5000 | H34: =(F34+G34)*(1+Inputs!$B$13) -> 683825.33

Sheet Dashboard
A1: Mutual Fund vs ETF: Fee Impact Demo
A3: Key Inputs | B3: Value | D3: Summary | E3: Mutual Fund | F3: ETF | G3: Difference | H3: Meaning
A4: Initial investment | B4: =Inputs!B4 -> 10000 | D4: Net return | E4: =Inputs!B12 -> 0.06 | F4: =Inputs!B13 -> 0.078 | G4: =F4-E4 -> 0.018 | H4: Return after fees
A5: Annual contribution | B5: =Inputs!B5 -> 5000 | D5: Ending value | E5: =INDEX('Yearly Calculation'!E:E, MATCH(Inputs!B6, 'Yearly Calculation'!A:A, 0)) -> 476443.3 | F5: =INDEX('Yearly Calculation'!H:H, MATCH(Inputs!B6, 'Yearly Calculation'!A:A, 0)) -> 683825.33 | G5: =F5-E5 -> 207382.03 | H5: Portfolio value after selected years
A6: Years | B6: =Inputs!B6 -> 30 | D6: Total contributed | E6: =Inputs!B4+(Inputs!B5*Inputs!B6) -> 160000 | F6: =E6 -> 160000 | G6: =F6-E6 -> 0 | H6: Initial investment + contributions
A7: Expected gross return | B7: =Inputs!B7 -> 0.08 | D7: Investment growth | E7: =E5-E6 -> 316443.3 | F7: =F5-F6 -> 523825.33 | G7: =F7-E7 -> 207382.03 | H7: Ending value minus contributions
A8: Mutual fund MER | B8: =Inputs!B8 -> 0.02 | D8: Extra ETF value | G8: =G5 -> 207382.03 | H8: ETF ending value minus mutual fund ending value
A9: ETF MER | B9: =Inputs!B9 -> 0.002 | D9: Fee drag vs ETF | G9: =G5/E5 -> 0.43527117 | H9: Lower final value due to higher fee
A12: Chart Data | B12: Ending Value | C12: Net Return
A13: Mutual Fund | B13: =E5 -> 476443.3 | C13: =E4 -> 0.06
A14: ETF | B14: =F5 -> 683825.33 | C14: =F4 -> 0.078
A15: Difference | B15: =G5 -> 207382.03 | C15: =G4 -> 0.018
A17: Plain English Takeaway
A18: Mutual funds can be useful, but higher fees reduce your final return.
A19: ETFs usually have lower MER, so more of the return stays invested.
A20: Small annual fee differences can become large over 20–30 years.

Sheet Instructions
A1: How to Use This Workbook
A3: Step | B3: Action | C3: Where | D3: Notes
A4: 1 | B4: Change the assumptions | C4: Inputs!B4:B9 | D4: Yellow cells are editable inputs.
A5: 2 | B5: Review yearly growth | C5: Yearly Calculation | D5: This shows how the investment grows each year.
A6: 3 | B6: Compare final results | C6: Dashboard | D6: Shows mutual fund vs ETF ending values.
A7: 4 | B7: Use in your video | C7: Dashboard | D7: Use the chart and summary as demo visuals.
A9: Important Disclaimer
A10: This workbook is for educational and demo purposes only. It is not financial advice. Actual investment returns, fees, taxes, and risks may differ. Please do your own research or speak with a qualified financial professional.
